hiwenet/__init__.py
hiwenet/__main__.py
hiwenet/_version.py
hiwenet/analyze_distance_behaviour.py
hiwenet/more_metrics.py
hiwenet/non_pairwise.py
hiwenet/pairwise_dist.py
hiwenet/test_hiwenet.py
hiwenet/test_medpy.py
hiwenet/utils.py
hiwenet-0.4.5.dist-info/LICENSE
hiwenet-0.4.5.dist-info/METADATA
hiwenet-0.4.5.dist-info/WHEEL
hiwenet-0.4.5.dist-info/entry_points.txt
hiwenet-0.4.5.dist-info/top_level.txt
hiwenet-0.4.5.dist-info/RECORD
