Metadata-Version: 2.1
Name: hiwenet
Version: 0.4.5
Summary: Histogram-weighted Networks for Feature Extraction and Advance Analysis in Neuroscience
Home-page: https://github.com/raamana/hiwenet
Author: Pradeep Reddy Raamana
Author-email: raamana@gmail.com
License: UNKNOWN
Platform: UNKNOWN
Classifier: Intended Audience :: Science/Research
Classifier: Programming Language :: Python
Classifier: Topic :: Software Development
Classifier: Topic :: Scientific/Engineering
Classifier: Operating System :: Microsoft :: Windows
Classifier: Operating System :: POSIX
Classifier: Operating System :: Unix
Classifier: Operating System :: MacOS
Classifier: Programming Language :: Python :: 3.6
Requires-Dist: numpy
Requires-Dist: pyradigm
Requires-Dist: nibabel
Requires-Dist: networkx
Requires-Dist: medpy
